{
  "757947": {
    "email": "viczoe019@gmail.com",
    "expires": "2025-07-10T16:41:40.144238",
    "activated": false
  },
  "656677": {
    "email": "viczoe019@gmail.com",
    "expires": "2025-07-10T16:44:13.648506",
    "activated": true
  },
  "118703": {
    "email": "viczoe019@gmail.com",
    "expires": "2025-08-09T17:24:20.886410",
    "activated": true
  },
  "536264": {
    "email": "op\\data-analyzer> python otp_manager.py",
    "expires": "2025-08-09T17:52:24.052404",
    "activated": false
  },
  "539470": {
    "email": "viczoe019@gmail.com",
    "expires": "2025-08-09T17:53:33.605055",
    "activated": true
  },
  "631519": {
    "email": "viczoe019@gmail.com",
    "expires": "2025-08-09T18:34:10.800899",
    "activated": true
  }
}